sklearn_cv_pandas/__init__.py
sklearn_cv_pandas/model.py
sklearn_cv_pandas/pandas_cv.py
sklearn_cv_pandas/preprocessing.py
sklearn_cv_pandas-0.0.12.dist-info/LICENSE
sklearn_cv_pandas-0.0.12.dist-info/METADATA
sklearn_cv_pandas-0.0.12.dist-info/WHEEL
sklearn_cv_pandas-0.0.12.dist-info/top_level.txt
sklearn_cv_pandas-0.0.12.dist-info/RECORD
