Metadata-Version: 2.1
Name: sklearn-cv-pandas
Version: 0.0.12
Summary: RandomizedSearchCV/GridSearchCV with pandas.DataFrame interface
Home-page: https://github.com/not-so-fat/sklearn_cv_pandas
Author: @not-so-fat
Classifier: Programming Language :: Python :: 3
Classifier: License :: OSI Approved :: MIT License
Classifier: Operating System :: OS Independent
Requires-Python: >=3.6
License-File: LICENSE
Requires-Dist: pandas (>=1.2.4)
Requires-Dist: scikit-learn (>=0.24.1)
